{
  "info": {
    "name": "Copliot Backend API",
    "description": "API collection for Copliot Backend",
    "schema": "https://schema.getpostman.com/json/collection/v2.1.0/collection.json"
  },
  "item": [
    {
      "name": "Authentication",
      "item": [
        {
          "name": "Request OTP",
          "request": {
            "method": "POST",
            "header": [
              {
                "key": "Content-Type",
                "value": "application/json"
              }
            ],
            "body": {
              "mode": "raw",
              "raw": "{\n  \"phoneNumber\": \"+1234567890\"\n}"
            },
            "url": {
              "raw": "http://localhost:8080/api/auth/otp/request",
              "protocol": "http",
              "host": ["localhost"],
              "port": "8080",
              "path": ["api", "auth", "otp", "request"]
            }
          }
        },
        {
          "name": "Verify OTP",
          "request": {
            "method": "POST",
            "header": [
              {
                "key": "Content-Type",
                "value": "application/json"
              }
            ],
            "body": {
              "mode": "raw",
              "raw": "{\n  \"phoneNumber\": \"+1234567890\",\n  \"code\": \"123456\"\n}"
            },
            "url": {
              "raw": "http://localhost:8080/api/auth/otp/verify",
              "protocol": "http",
              "host": ["localhost"],
              "port": "8080",
              "path": ["api", "auth", "otp", "verify"]
            }
          }
        },
        {
          "name": "Resend OTP",
          "request": {
            "method": "POST",
            "header": [
              {
                "key": "Content-Type",
                "value": "application/json"
              }
            ],
            "body": {
              "mode": "raw",
              "raw": "{\n  \"phoneNumber\": \"+1234567890\"\n}"
            },
            "url": {
              "raw": "http://localhost:8080/api/auth/otp/resend",
              "protocol": "http",
              "host": ["localhost"],
              "port": "8080",
              "path": ["api", "auth", "otp", "resend"]
            }
          }
        },
        {
          "name": "Partner Login",
          "request": {
            "method": "POST",
            "header": [
              {
                "key": "Content-Type",
                "value": "application/json"
              }
            ],
            "body": {
              "mode": "raw",
              "raw": "{\n  \"username\": \"testpartner\",\n  \"password\": \"password123\"\n}"
            },
            "url": {
              "raw": "http://localhost:8080/api/auth/partner/login",
              "protocol": "http",
              "host": ["localhost"],
              "port": "8080",
              "path": ["api", "auth", "partner", "login"]
            }
          }
        }
      ]
    },
    {
      "name": "Partner",
      "item": [
        {
          "name": "Register Partner",
          "request": {
            "method": "POST",
            "header": [],
            "body": {
              "mode": "formdata",
              "formdata": [
                {
                  "key": "username",
                  "value": "testpartner",
                  "type": "text"
                },
                {
                  "key": "password",
                  "value": "password123",
                  "type": "text"
                },
                {
                  "key": "businessName",
                  "value": "Test Business",
                  "type": "text"
                },
                {
                  "key": "email",
                  "value": "test@example.com",
                  "type": "text"
                },
                {
                  "key": "logo",
                  "type": "file",
                  "src": []
                }
              ]
            },
            "url": {
              "raw": "http://localhost:8080/api/partners/register",
              "protocol": "http",
              "host": ["localhost"],
              "port": "8080",
              "path": ["api", "partners", "register"]
            }
          }
        },
        {
          "name": "Get Partner Profile",
          "request": {
            "method": "GET",
            "header": [
              {
                "key": "Authorization",
                "value": "Bearer {{partner_token}}",
                "type": "text"
              }
            ],
            "url": {
              "raw": "http://localhost:8080/api/partners/profile",
              "protocol": "http",
              "host": ["localhost"],
              "port": "8080",
              "path": ["api", "partners", "profile"]
            }
          }
        },
        {
          "name": "Update Partner Profile",
          "request": {
            "method": "PUT",
            "header": [
              {
                "key": "Authorization",
                "value": "Bearer {{partner_token}}",
                "type": "text"
              }
            ],
            "body": {
              "mode": "formdata",
              "formdata": [
                {
                  "key": "businessName",
                  "value": "Updated Business",
                  "type": "text"
                },
                {
                  "key": "email",
                  "value": "updated@example.com",
                  "type": "text"
                }
              ]
            },
            "url": {
              "raw": "http://localhost:8080/api/partners/profile",
              "protocol": "http",
              "host": ["localhost"],
              "port": "8080",
              "path": ["api", "partners", "profile"]
            }
          }
        }
      ]
    },
    {
      "name": "User",
      "item": [
        {
          "name": "Get User Profile",
          "request": {
            "method": "GET",
            "header": [
              {
                "key": "Authorization",
                "value": "Bearer {{user_token}}",
                "type": "text"
              }
            ],
            "url": {
              "raw": "http://localhost:8080/api/users/profile",
              "protocol": "http",
              "host": ["localhost"],
              "port": "8080",
              "path": ["api", "users", "profile"]
            }
          }
        },
        {
          "name": "Update User Profile",
          "request": {
            "method": "PUT",
            "header": [
              {
                "key": "Authorization",
                "value": "Bearer {{user_token}}",
                "type": "text"
              },
              {
                "key": "Content-Type",
                "value": "application/json"
              }
            ],
            "body": {
              "mode": "raw",
              "raw": "{\n  \"name\": \"John Doe\",\n  \"email\": \"john@example.com\"\n}"
            },
            "url": {
              "raw": "http://localhost:8080/api/users/profile",
              "protocol": "http",
              "host": ["localhost"],
              "port": "8080",
              "path": ["api", "users", "profile"]
            }
          }
        }
      ]
    }
  ],
  "variable": [
    {
      "key": "user_token",
      "value": "",
      "type": "string"
    },
    {
      "key": "partner_token",
      "value": "",
      "type": "string"
    }
  ]
}
